pytorch_symbolic/__init__.py
pytorch_symbolic/code_generator.py
pytorch_symbolic/config.py
pytorch_symbolic/functions_utility.py
pytorch_symbolic/graph_algorithms.py
pytorch_symbolic/model_tools.py
pytorch_symbolic/symbolic_api_2.py
pytorch_symbolic/symbolic_data.py
pytorch_symbolic/symbolic_model.py
pytorch_symbolic/useful_layers.py
pytorch_symbolic-1.1.1.dist-info/METADATA
pytorch_symbolic-1.1.1.dist-info/WHEEL
pytorch_symbolic-1.1.1.dist-info/licenses/LICENSE.txt
pytorch_symbolic-1.1.1.dist-info/RECORD
