Metadata-Version: 2.4
Name: pytorch-symbolic
Version: 1.1.1
Summary: Symbolic API for model creation in PyTorch.
Project-URL: Home, https://github.com/gahaalt/pytorch-symbolic
Project-URL: Documentation, https://github.com/sjmikler/pytorch-symbolic/blob/main/docs
Author-email: Szymon Mikler <sjmikler@gmail.com>
License: MIT
License-File: LICENSE.txt
Classifier: License :: OSI Approved :: MIT License
Classifier: Programming Language :: Python :: 3
Classifier: Programming Language :: Python :: 3.7
Classifier: Programming Language :: Python :: 3.8
Classifier: Programming Language :: Python :: 3.9
Classifier: Programming Language :: Python :: 3.10
Classifier: Programming Language :: Python :: 3.11
Classifier: Programming Language :: Python :: 3.12
Classifier: Programming Language :: Python :: 3.13
Requires-Python: >=3.7
Requires-Dist: torch
Provides-Extra: dev
Requires-Dist: hatch; extra == 'dev'
Requires-Dist: pyright; extra == 'dev'
Requires-Dist: pytest; extra == 'dev'
Requires-Dist: pytest-cov; extra == 'dev'
Requires-Dist: ruff; extra == 'dev'
Requires-Dist: twine; extra == 'dev'
Provides-Extra: full
Requires-Dist: matplotlib; extra == 'full'
Requires-Dist: networkx; extra == 'full'
Requires-Dist: scipy; extra == 'full'
